typed_descriptors/__init__.py
typed_descriptors/attr.py
typed_descriptors/base.py
typed_descriptors/mypy_plugin.py
typed_descriptors/prop.py
typed_descriptors/py.typed
typed_descriptors-1.2.2.post4.dist-info/LICENSE
typed_descriptors-1.2.2.post4.dist-info/METADATA
typed_descriptors-1.2.2.post4.dist-info/WHEEL
typed_descriptors-1.2.2.post4.dist-info/top_level.txt
typed_descriptors-1.2.2.post4.dist-info/RECORD
